fers-0.1.48.dist-info/licenses/LICENSE
fers_core/__init__.py
fers_core/solver.py
fers_core/fers/__init__.py
fers_core/fers/deformation_utils.py
fers_core/fers/fers.py
fers_core/imperfections/__init__.py
fers_core/imperfections/imperfectioncase.py
fers_core/imperfections/rotationimperfection.py
fers_core/imperfections/translationimperfection.py
fers_core/loads/__init__.py
fers_core/loads/distributedload.py
fers_core/loads/distributionshape.py
fers_core/loads/enums.py
fers_core/loads/loadcase.py
fers_core/loads/loadcombination.py
fers_core/loads/nodalload.py
fers_core/loads/nodalmoment.py
fers_core/members/__init__.py
fers_core/members/enums.py
fers_core/members/material.py
fers_core/members/member.py
fers_core/members/memberhinge.py
fers_core/members/memberset.py
fers_core/members/section.py
fers_core/members/shapecommand.py
fers_core/members/shapepath.py
fers_core/nodes/__init__.py
fers_core/nodes/node.py
fers_core/results/__init__.py
fers_core/results/member.py
fers_core/results/nodes.py
fers_core/results/results.py
fers_core/results/resultsbundle.py
fers_core/results/resultssummary.py
fers_core/results/singleresults.py
fers_core/settings/__init__.py
fers_core/settings/anlysis_options.py
fers_core/settings/enums.py
fers_core/settings/general_info.py
fers_core/settings/settings.py
fers_core/supports/__init__.py
fers_core/supports/nodalsupport.py
fers_core/supports/support_utils.py
fers_core/supports/supportcondition.py
fers_core/types/__init__.py
fers_core/types/pydantic_models.py
fers_core/validation/__init__.py
fers_core/validation/checktype.py
fers_core/validation/validationcheck.py
tests/__init__.py
tests/common_functions.py
tests/beam_equation_checks/__init__.py
tests/beam_equation_checks/test_beam_equations.py
tests/functionality/__init__.py
tests/functionality/test_functionality.py
fers-0.1.48.dist-info/METADATA
fers-0.1.48.dist-info/WHEEL
fers-0.1.48.dist-info/top_level.txt
fers-0.1.48.dist-info/RECORD
