Metadata-Version: 2.4
Name: FERS
Version: 0.1.48
Summary: Finite Element Method library written in Rust with Python interface
Home-page: https://github.com/jeroen124/FERS_core
Author: Jeroen Hermsen
Author-email: info@ferscloud.com
Classifier: Programming Language :: Python :: 3
Classifier: Programming Language :: Rust
Classifier: License :: OSI Approved :: BSD License
Classifier: Operating System :: OS Independent
Requires-Python: >=3.12
License-File: LICENSE
Requires-Dist: numpy==2.1.2
Requires-Dist: matplotlib==3.9.2
Requires-Dist: ujson==5.10.0
Requires-Dist: sectionproperties==3.7.0
Requires-Dist: pyvista==0.44.2
Requires-Dist: fers_calculations==0.1.63
Requires-Dist: pydantic==2.10.4
Requires-Dist: scipy==1.14.1
Requires-Dist: pre_commit==4.0.0
Dynamic: author
Dynamic: author-email
Dynamic: classifier
Dynamic: description
Dynamic: description-content-type
Dynamic: home-page
Dynamic: license-file
Dynamic: requires-dist
Dynamic: requires-python
Dynamic: summary
